microcosm_pubsub/__init__.py
microcosm_pubsub/backoff.py
microcosm_pubsub/batch.py
microcosm_pubsub/codecs.py
microcosm_pubsub/constants.py
microcosm_pubsub/consumer.py
microcosm_pubsub/context.py
microcosm_pubsub/daemon.py
microcosm_pubsub/decorators.py
microcosm_pubsub/dispatcher.py
microcosm_pubsub/envelope.py
microcosm_pubsub/errors.py
microcosm_pubsub/fields.py
microcosm_pubsub/main.py
microcosm_pubsub/message.py
microcosm_pubsub/metrics.py
microcosm_pubsub/producer.py
microcosm_pubsub/reader.py
microcosm_pubsub/registry.py
microcosm_pubsub/result.py
microcosm_pubsub/sentry.py
microcosm_pubsub/tracing.py
microcosm_pubsub/chain/__init__.py
microcosm_pubsub/chain/chain.py
microcosm_pubsub/chain/context.py
microcosm_pubsub/chain/context_decorators.py
microcosm_pubsub/chain/decorators.py
microcosm_pubsub/chain/exceptions.py
microcosm_pubsub/chain/statements/__init__.py
microcosm_pubsub/chain/statements/assign.py
microcosm_pubsub/chain/statements/call.py
microcosm_pubsub/chain/statements/case.py
microcosm_pubsub/chain/statements/for_each.py
microcosm_pubsub/chain/statements/switch.py
microcosm_pubsub/chain/statements/try_chain.py
microcosm_pubsub/chain/statements/when.py
microcosm_pubsub/conventions/__init__.py
microcosm_pubsub/conventions/lifecycle.py
microcosm_pubsub/conventions/messages.py
microcosm_pubsub/conventions/naming.py
microcosm_pubsub/handlers/__init__.py
microcosm_pubsub/handlers/chain_handlers.py
microcosm_pubsub/handlers/publish_batch_message.py
microcosm_pubsub/handlers/uri_handler.py
microcosm_pubsub/matchers/__init__.py
microcosm_pubsub/matchers/message.py
microcosm_pubsub/matchers/publishing.py
microcosm_pubsub-3.0.0.dist-info/LICENSE
microcosm_pubsub-3.0.0.dist-info/METADATA
microcosm_pubsub-3.0.0.dist-info/WHEEL
microcosm_pubsub-3.0.0.dist-info/entry_points.txt
microcosm_pubsub-3.0.0.dist-info/top_level.txt
microcosm_pubsub-3.0.0.dist-info/RECORD
